lttb/__init__.py
lttb/lttb.py
lttb/validators.py
lttb-0.3.2.dist-info/WHEEL
lttb-0.3.2.dist-info/METADATA
lttb-0.3.2.dist-info/RECORD
