Metadata-Version: 2.1
Name: lttb
Version: 0.3.2
Summary: Largest-Triangle-Three-Buckets algorithm for downsampling time series-like data
Author-email: JA Viljoen <javiljoen@javiljoen.net>
Requires-Python: ~=3.8
Classifier: Development Status :: 4 - Beta
Classifier: Intended Audience :: Financial and Insurance Industry
Classifier: Intended Audience :: Information Technology
Classifier: Intended Audience :: Science/Research
Classifier: License :: OSI Approved :: MIT License
Classifier: Operating System :: OS Independent
Classifier: Topic :: Office/Business :: Financial :: Investment
Classifier: Topic :: Scientific/Engineering :: Visualization
Requires-Dist: numpy ~= 1.17
Requires-Dist: black ~= 24.2 ; extra == "dev"
Requires-Dist: flake8 ~= 7.0 ; extra == "dev"
Requires-Dist: flake8-bugbear ~= 23.7 ; extra == "dev"
Requires-Dist: flit ~= 3.9 ; extra == "dev"
Requires-Dist: isort ~= 5.6 ; extra == "dev"
Requires-Dist: pytest ~= 8.3 ; extra == "test"
Requires-Dist: hypothesis[numpy] ~= 6.0 ; extra == "test"
Project-URL: Homepage, https://sr.ht/~javiljoen/lttb/
Project-URL: MailingList, https://lists.sr.ht/~javiljoen/lttb-devel
Project-URL: Source, https://git.sr.ht/~javiljoen/lttb-numpy
Project-URL: Tracker, https://codeberg.org/javiljoen/lttb-numpy/issues
Provides-Extra: dev
Provides-Extra: test
